ark/__init__.py
ark/__main__.py
ark/events.py
ark/extensions.py
ark/filters.py
ark/hashes.py
ark/nodes.py
ark/renderers.py
ark/site.py
ark/templates.py
ark/utils.py
ark/bundle/.DS_Store
ark/bundle/site.py
ark/bundle/inc/menu.md
ark/bundle/lib/.DS_Store
ark/bundle/lib/debug/license.txt
ark/bundle/lib/debug/readme.md
ark/bundle/lib/debug/resources/debug.css
ark/bundle/lib/debug/resources/pygments.css
ark/bundle/lib/debug/templates/node.ibis
ark/bundle/lib/graphite/license.txt
ark/bundle/lib/graphite/readme.md
ark/bundle/lib/graphite/resources/assets/code.js
ark/bundle/lib/graphite/resources/assets/fonts.css
ark/bundle/lib/graphite/resources/assets/graphite.css
ark/bundle/lib/graphite/resources/assets/pygments.css
ark/bundle/lib/graphite/resources/assets/fonts/CrimsonText-Bold.ttf
ark/bundle/lib/graphite/resources/assets/fonts/CrimsonText-Bold.woff2
ark/bundle/lib/graphite/resources/assets/fonts/CrimsonText-BoldItalic.ttf
ark/bundle/lib/graphite/resources/assets/fonts/CrimsonText-BoldItalic.woff2
ark/bundle/lib/graphite/resources/assets/fonts/CrimsonText-Italic.ttf
ark/bundle/lib/graphite/resources/assets/fonts/CrimsonText-Italic.woff2
ark/bundle/lib/graphite/resources/assets/fonts/CrimsonText-Regular.ttf
ark/bundle/lib/graphite/resources/assets/fonts/CrimsonText-Regular.woff2
ark/bundle/lib/graphite/resources/assets/fonts/CrimsonText-SemiBold.ttf
ark/bundle/lib/graphite/resources/assets/fonts/CrimsonText-SemiBold.woff2
ark/bundle/lib/graphite/resources/assets/fonts/CrimsonText-SemiBoldItalic.ttf
ark/bundle/lib/graphite/resources/assets/fonts/CrimsonText-SemiBoldItalic.woff2
ark/bundle/lib/graphite/resources/assets/fonts/OFL.txt
ark/bundle/lib/graphite/templates/node.ibis
ark/bundle/src/about.md
ark/bundle/src/index.stx
ark/bundle/src/parent.md
ark/bundle/src/parent/child-one.md
ark/bundle/src/parent/child-two.md
ark/cli/__init__.py
ark/cli/add.py
ark/cli/build.py
ark/cli/clear.py
ark/cli/deploy.py
ark/cli/init.py
ark/cli/open.py
ark/cli/serve.py
ark/cli/tree.py
ark-7.7.0.dist-info/METADATA
ark-7.7.0.dist-info/WHEEL
ark-7.7.0.dist-info/entry_points.txt
ark-7.7.0.dist-info/top_level.txt
ark-7.7.0.dist-info/RECORD
