Metadata-Version: 2.1
Name: ark
Version: 7.7.0
Summary: A static website generator for people who enjoy the simpler things in life.
Home-page: https://github.com/dmulholl/ark
Author: Darren Mulholland
License: Public Domain
Classifier: Programming Language :: Python :: 3
Classifier: Operating System :: OS Independent
Classifier: License :: Public Domain
Classifier: Topic :: Text Processing :: Markup :: HTML
Requires-Python: >=3.10
Requires-Dist: markdown ~=3.0
Requires-Dist: pygments ~=2.0
Requires-Dist: pyyaml ~=6.0
Requires-Dist: jinja2 ~=3.0
Requires-Dist: syntext ~=3.0
Requires-Dist: ibis ~=3.0
Requires-Dist: shortcodes ~=5.1
Requires-Dist: argslib ~=2.0
Requires-Dist: colorama ~=0.4
